{
  "mode": "pre",
  "tag": "alpha",
  "initialVersions": {
    "@doxajs/field-guide": "0.1.0",
    "@doxajs/persistence-reference-app": "0.1.0",
    "@doxajs/reference-app": "0.1.0",
    "@doxajs/praxis": "0.1.0-alpha.0",
    "@doxajs/auth-postgres": "0.1.0-alpha.0",
    "@doxajs/compiler": "0.1.0-alpha.0",
    "@doxajs/core": "0.1.0-alpha.0",
    "@doxajs/http-hono": "0.1.0-alpha.0",
    "@doxajs/manifest": "0.1.0-alpha.0",
    "@doxajs/postgres-drizzle": "0.1.0-alpha.0",
    "@doxajs/queue-pg-boss": "0.1.0-alpha.0",
    "@doxajs/runtime": "0.1.0-alpha.0",
    "@doxajs/sendgrid": "0.1.0-alpha.0",
    "@doxajs/testing": "0.1.0-alpha.0",
    "@doxajs/twilio-sms": "0.1.0-alpha.0",
    "@doxajs/theoria": "0.1.0-alpha.0"
  },
  "changesets": []
}
